fastapi_health_monitor/__init__.py
fastapi_health_monitor/checkrunner.py
fastapi_health_monitor/constants.py
fastapi_health_monitor/healthmonitor.py
fastapi_health_monitor/manager.py
fastapi_health_monitor/models.py
fastapi_health_monitor/settings.py
fastapi_health_monitor-1.0.1.dist-info/LICENSE
fastapi_health_monitor-1.0.1.dist-info/METADATA
fastapi_health_monitor-1.0.1.dist-info/WHEEL
fastapi_health_monitor-1.0.1.dist-info/RECORD
