Metadata-Version: 2.1
Name: fastapi-health-monitor
Version: 1.0.1
Summary: A health monitor for FastAPI applications.
License: MIT
Author: Adam Kirchberger
Author-email: adamkirchberger@users.noreply.github.com
Requires-Python: >=3.10,<4.0
Classifier: Framework :: FastAPI
Classifier: Intended Audience :: Developers
Classifier: License :: OSI Approved :: MIT License
Classifier: Operating System :: OS Independent
Classifier: Programming Language :: Python :: 3
Classifier: Programming Language :: Python :: 3.10
Classifier: Programming Language :: Python :: 3.11
Classifier: Topic :: Software Development
Requires-Dist: fastapi (>=0.101.0,<0.102.0)
Requires-Dist: httpx (>=0.24.1,<0.25.0)
Requires-Dist: pydantic (>=2.1.1,<3.0.0)
Requires-Dist: pydantic-settings (>=2.0.2,<3.0.0)
